MANIFEST.in
README.md
pefile.py
setup.cfg
setup.py
zipextimporter.py
cachetools/__init__.py
cachetools/abc.py
cachetools/cache.py
cachetools/decorators.py
cachetools/func.py
cachetools/keys.py
cachetools/lfu.py
cachetools/lru.py
cachetools/rr.py
cachetools/ttl.py
ordlookup/__init__.py
ordlookup/oleaut32.py
ordlookup/ws2_32.py
pexe38/__init__.py
pexe38/__main__.py
pexe38/_wapi.py
pexe38/boot_common.py
pexe38/boot_ctypes_com_server.py
pexe38/boot_service.py
pexe38/build_exe.py
pexe38/distutils_buildexe.py
pexe38/dllfinder.py
pexe38/hooks.py
pexe38/icons.py
pexe38/mf3.py
pexe38/mf34.py
pexe38/patch_distutils.py
pexe38/pewalker.py
pexe38/pexe38_distutils.py
pexe38/resources.py
pexe38/runtime.py
pexe38/setup_template.py
pexe38/versioninfo.py
pexe38.egg-info/PKG-INFO
pexe38.egg-info/SOURCES.txt
pexe38.egg-info/dependency_links.txt
pexe38.egg-info/entry_points.txt
pexe38.egg-info/requires.txt
pexe38.egg-info/top_level.txt
source/MemoryModule.c
source/MemoryModule.h
source/MyLoadLibrary.c
source/MyLoadLibrary.h
source/Python-dynload.h
source/_memimporter.c
source/actctx.c
source/actctx.h
source/dll.c
source/icon.rc
source/icon1.ico
source/python-dynload.c
source/resource.h
source/run.c
source/run_ctypes_dll.c
source/run_w.c
source/start.c