Metadata-Version: 1.1
Name: pexe38
Version: 1.3
Summary: Python38 to Exe
Home-page: http://www.pexe38.org/
Author: darkArp
Author-email: marionascimento@itsec.bz
License: MIT/X11
Download-URL: https://github.com/darkarp/pexe38/archive/v1.3.zip
Platform: Windows
Classifier: Development Status :: 4 - Beta
Classifier: Environment :: Console
Classifier: License :: OSI Approved :: MIT License
Classifier: License :: OSI Approved :: Mozilla Public License 2.0 (MPL 2.0)
Classifier: Operating System :: Microsoft :: Windows
Classifier: Programming Language :: C
Classifier: Programming Language :: Python :: 3
Classifier: Programming Language :: Python :: 3.7
Classifier: Programming Language :: Python :: Implementation :: CPython
Classifier: Topic :: Software Development
Classifier: Topic :: Software Development :: Libraries
Classifier: Topic :: Software Development :: Libraries :: Python Modules
Classifier: Topic :: System :: Software Distribution
Classifier: Topic :: Utilities
